Main.py
SeleniumCommonSetting.py
SeleniumCommonSetting-1.2.1.dist-info/LICENSE
SeleniumCommonSetting-1.2.1.dist-info/METADATA
SeleniumCommonSetting-1.2.1.dist-info/WHEEL
SeleniumCommonSetting-1.2.1.dist-info/top_level.txt
SeleniumCommonSetting-1.2.1.dist-info/RECORD
