Metadata-Version: 2.1
Name: SeleniumCommonSetting
Version: 1.2.1
Summary: 常用的selenium-webdriver设置
Home-page: https://gitee.com/joeyoung18/SeleniumCommonSetting.git
Author: JoeYoung
Author-email: 1022104172@qq.com
License: MIT Licence
Keywords: selenium
Platform: UNKNOWN
License-File: LICENSE
